fastyr/__init__.py
fastyr/api/__init__.py
fastyr/api/main.py
fastyr/api/graphql/__init__.py
fastyr/api/graphql/resolvers.py
fastyr/api/graphql/schema.py
fastyr/core/__init__.py
fastyr/core/config.py
fastyr/core/exceptions.py
fastyr/core/contracts/__init__.py
fastyr/core/contracts/auth.py
fastyr/core/contracts/constants.py
fastyr/core/contracts/dto.py
fastyr/core/contracts/request_dtos.py
fastyr/core/contracts/response_dtos.py
fastyr/domain/__init__.py
fastyr/infrastructure/__init__.py
fastyr/services/__init__.py
fastyr_ai_pipeline-0.1.0.dist-info/METADATA
fastyr_ai_pipeline-0.1.0.dist-info/WHEEL
fastyr_ai_pipeline-0.1.0.dist-info/top_level.txt
fastyr_ai_pipeline-0.1.0.dist-info/RECORD
