Metadata-Version: 2.4
Name: fastyr-ai-pipeline
Version: 0.1.0
Summary: A flexible AI pipeline for STT, LLM, and TTS
Home-page: https://github.com/cuuj69/fastyr
Author: William Jefferson Mensah
Author-email: mensahjefferson69@gmail.com
License: MIT
Classifier: Development Status :: 4 - Beta
Classifier: Intended Audience :: Developers
Classifier: Topic :: Software Development :: Libraries :: Python Modules
Classifier: Topic :: Scientific/Engineering :: Artificial Intelligence
Classifier: License :: OSI Approved :: MIT License
Classifier: Programming Language :: Python :: 3
Classifier: Programming Language :: Python :: 3.7
Classifier: Programming Language :: Python :: 3.8
Classifier: Programming Language :: Python :: 3.9
Classifier: Programming Language :: Python :: 3.10
Classifier: Programming Language :: Python :: 3.11
Classifier: Operating System :: OS Independent
Classifier: Framework :: FastAPI
Requires-Python: >=3.7
Requires-Dist: requests
Requires-Dist: fastapi>=0.68.0
Requires-Dist: uvicorn[standard]>=0.15.0
Requires-Dist: sqlalchemy[asyncio]>=1.4.0
Requires-Dist: alembic>=1.7.0
Requires-Dist: strawberry-graphql>=0.96.0
Requires-Dist: sentry-sdk>=1.5.0
Requires-Dist: structlog>=21.1.0
Requires-Dist: dependency-injector>=4.39.1
Requires-Dist: python-jose[cryptography]>=3.3.0
Requires-Dist: passlib>=1.7.4
Requires-Dist: python-multipart>=0.0.5
Requires-Dist: asyncpg>=0.25.0
Requires-Dist: prometheus-client>=0.12.0
Requires-Dist: gunicorn>=20.1.0
Requires-Dist: psycopg2-binary>=2.9.1
Requires-Dist: aiosqlite>=0.17.0
Requires-Dist: aiofiles>=23.2.1
Requires-Dist: PyJWT>=2.0.0
Provides-Extra: dev
Requires-Dist: pytest>=7.0.0; extra == "dev"
Requires-Dist: pytest-cov>=4.0.0; extra == "dev"
Requires-Dist: pytest-asyncio>=0.21.0; extra == "dev"
Requires-Dist: pytest-mock>=3.10.0; extra == "dev"
Requires-Dist: coverage>=7.2.0; extra == "dev"
Requires-Dist: httpx>=0.24.0; extra == "dev"
Requires-Dist: aiohttp>=3.8.0; extra == "dev"
Requires-Dist: pytest-env>=1.0.0; extra == "dev"
Dynamic: author
Dynamic: author-email
Dynamic: classifier
Dynamic: description
Dynamic: description-content-type
Dynamic: home-page
Dynamic: license
Dynamic: provides-extra
Dynamic: requires-dist
Dynamic: requires-python
Dynamic: summary
